djangocms_testing/__init__.py
djangocms_testing/conf.py
djangocms_testing/integrity.py
djangocms_testing/models.py
djangocms_testing/templates/djangocms_testing/generic_page.html
djangocms_testing-0.1.dist-info/METADATA
djangocms_testing-0.1.dist-info/RECORD
djangocms_testing-0.1.dist-info/WHEEL
djangocms_testing-0.1.dist-info/top_level.txt
