Metadata-Version: 2.1
Name: djangocms-testing
Version: 0.1
Summary: Testing utilities for Django CMS
Home-page: https://github.com/nicolaslara/djangocms_testing/
Author: Nicolas Lara
Author-email: nicolas@lincolnloop.com
License: BSD
Platform: UNKNOWN
Classifier: Development Status :: 4 - Beta
Classifier: Environment :: Web Environment
Classifier: License :: OSI Approved :: BSD License
Classifier: Operating System :: OS Independent
Classifier: Programming Language :: Python
Classifier: Programming Language :: Python :: 3.6
Classifier: Topic :: Software Development :: Testing
Classifier: Framework :: Django
Requires-Python: >=3.6
Requires-Dist: django-cms (>=3.4.5)
Requires-Dist: PyYAML (>=3.12)
